pyapcsc/__init__.py
pyapcsc/__main__.py
pyapcsc/api.py
pyapcsc/client.py
pyapcsc/dtos.py
pyapcsc/exceptions.py
pyapcsc/login_helper.py
pyapcsc-0.1.8.dist-info/LICENSE
pyapcsc-0.1.8.dist-info/METADATA
pyapcsc-0.1.8.dist-info/WHEEL
pyapcsc-0.1.8.dist-info/top_level.txt
pyapcsc-0.1.8.dist-info/RECORD
